{
  "plumbers": [
    {
      "id": 1,
      "name": "Maude"
    },
    {
      "id": 2,
      "name": "Merle"
    }
  ],
  "completions": [
    {
      "serviceRequest": "1",
      "plumber": "1",
      "id": 1
    },
    {
      "serviceRequest": "1",
      "plumber": "1",
      "id": 2
    },
    {
      "serviceRequest": "1",
      "plumber": "1",
      "id": 3
    },
    {
      "serviceRequest": "1",
      "plumber": "1",
      "id": 4
    },
    {
      "serviceRequest": "1",
      "plumber": "2",
      "id": 5
    },
    {
      "serviceRequest": "1",
      "plumber": "1",
      "id": 6
    },
    {
      "serviceRequest": "1",
      "plumber": "2",
      "id": 7
    },
    {
      "serviceRequest": "1",
      "plumber": "1",
      "id": 8
    },
    {
      "serviceRequest": "1",
      "plumber": "2",
      "id": 9
    },
    {
      "serviceRequest": "1",
      "plumber": "1",
      "id": 10
    },
    {
      "serviceRequest": "1",
      "plumber": "1",
      "id": 11
    },
    {
      "serviceRequest": "2",
      "plumber": "1",
      "id": 12
    },
    {
      "serviceRequest": "2",
      "plumber": "2",
      "id": 13
    }
  ],
  "requests": [
    {
      "id": 3,
      "description": "Kitchen sink fell through countertop",
      "address": "321 Rocket Rd",
      "budget": 550,
      "neededBy": "2022-11-01"
    },
    {
      "description": "Water running nonstop in toilet after flush",
      "address": "2016 Vanderbilt Way ",
      "budget": "350",
      "neededBy": "2022-11-04",
      "id": 6
    },
    {
      "description": "Bathtub is dripping",
      "address": "505 Baseball Dr",
      "budget": "350",
      "neededBy": "2022-11-12",
      "id": 7
    },
    {
      "description": "hot water not working",
      "address": "123 sunshine ave",
      "budget": "500",
      "neededBy": "2023-09-08",
      "id": 8
    },
    {
      "description": "ffgdfg",
      "address": "fgdfgf",
      "budget": "444",
      "neededBy": "2022-11-03",
      "id": 9
    }
  ]
}